leechcorepyc/FTD3XX.dll
leechcorepyc/FTD3XXWU.dll
leechcorepyc/leechcore.dll
leechcorepyc/leechcorepyc.pyd
leechcorepyc/leechcore_device_hvsavedstate.dll
leechcorepyc/leechcore_device_rawtcp.dll
leechcorepyc/leechcore_driver.dll
leechcorepyc/vcruntime140.dll
leechcorepyc/__init__.py
leechcorepyc-2.22.6.dist-info/LICENSE
leechcorepyc-2.22.6.dist-info/METADATA
leechcorepyc-2.22.6.dist-info/RECORD
leechcorepyc-2.22.6.dist-info/top_level.txt
leechcorepyc-2.22.6.dist-info/WHEEL
leechcorepyc-2.22.6.dist-info/RECORD
