Metadata-Version: 1.2
Name: leechcorepyc
Version: 2.22.6
Summary: LeechCore for Python
Home-page: https://github.com/ufrisk/LeechCore
Author: Ulf Frisk
Author-email: pcileech@frizk.net
License: GNU General Public License v3.0
Platform: manylinux1_x86_64
Classifier: Programming Language :: C
Classifier: Programming Language :: Python :: 3
Classifier: License :: OSI Approved :: GNU General Public License v3 (GPLv3)
Classifier: Operating System :: POSIX :: Linux
Requires-Python: >=3.6
